my_history/__init__.py
my_history/cli.py
nicou11_history-0.1.0.dist-info/METADATA
nicou11_history-0.1.0.dist-info/WHEEL
nicou11_history-0.1.0.dist-info/entry_points.txt
nicou11_history-0.1.0.dist-info/top_level.txt
nicou11_history-0.1.0.dist-info/RECORD
